README.md
setup.py
bin/slmr
slmr/__init__.py
slmr.egg-info/PKG-INFO
slmr.egg-info/SOURCES.txt
slmr.egg-info/dependency_links.txt
slmr.egg-info/not-zip-safe
slmr.egg-info/top_level.txt
slmr/LMRt/__init__.py
slmr/LMRt/load_gridded_data.py
slmr/LMRt/utils.py
slmr/LMRt/cfg/cfg_template.yml
slmr/visual/__init__.py