Metadata-Version: 2.1
Name: slmr
Version: 0.3.5
Summary: A scripting system for the Last Millennium Reanalysis (LMR) project.
Home-page: https://github.com/fzhu2e/slmr
Author: Feng Zhu
Author-email: fengzhu@usc.edu
License: MIT license
Keywords: slmr
Platform: UNKNOWN
Classifier: License :: OSI Approved :: MIT License
Classifier: Natural Language :: English
Classifier: Programming Language :: Python :: 3
Classifier: Programming Language :: Python :: 3.6
